dbz_python-0.2.1.dist-info/METADATA
dbz_python-0.2.1.dist-info/WHEEL
dbz_python/__init__.py
dbz_python/dbz_python.cpython-39-x86_64-linux-gnu.so
dbz_python-0.2.1.dist-info/RECORD
