Metadata-Version: 2.1
Name: dbz-python
Version: 0.2.1
Classifier: Programming Language :: Rust
Classifier: Programming Language :: Python :: Implementation :: CPython
Classifier: Programming Language :: Python :: Implementation :: PyPy
Summary: Python library written in Rust for working with the Databento Binary Encoding (DBZ) format
Author: Databento <support@databento.com>
Author-email: Databento <support@databento.com>
License: Apache-2.0
Requires-Python: >=3.7
Project-URL: Source Code, https://github.com/databento/dbz
